{"id":"879A4EA2-A19D-4407-B710-460A147BE311","validationEntity":{"analysedDataType":"auto","dataResult":{}},"modelEntity":{"createdDate":"2021-07-29T07:29:16Z","id":"7F97AB81-3290-43D1-9F12-9533AF369F72","experimentID":"879A4EA2-A19D-4407-B710-460A147BE311","title":"","modifiedDate":"2021-07-29T07:29:16Z","preferredFilename":"","version":"1.0","modelURL":"Models\/MyOngDogClassifier%201.mlmodel"},"version":"1.0","settingEntity":{"taskType":"imageClassifier","augmentations":[],"styleTransferAlgorithmType":"image","iterationCount":25,"transferLearningEmbeddingType":"dynamic","harVideoAugmentations":0,"algorithmType":"maxEnt","seedType":"default","featureNames":[]},"state":"trained","trainingEntity":{"finishTime":"2021-07-29T07:29:42Z","recipeTrainingResults":{"imageClassifier":{"confusionMatrix":[{"expected":"Dog","actual":"Dog","count":42},{"expected":"Ong","actual":"Ong","count":60}],"statsByLabel":{"Dog":{"count":42,"precisionRecall":{"success":{"recall":1,"precision":1}}},"Ong":{"count":60,"precisionRecall":{"success":{"recall":1,"precision":1}}}},"accuracy":1}},"dataResult":{"itemsCount":116,"dataURL":"file:\/\/\/Users\/beomsookim\/Desktop\/IOS_FastCampus\/CoreML\/Ongs-100\/","classesCount":2,"dataSourceID":"180EE8B1-3F39-48A8-A1CC-1F05EEA48E37","analysis":{"summary":{"canUseValidation":1,"classCount":2,"sampleCount":116},"issues":[{"description":"2 classes found, including Ong, Dog","severity":"debug"},{"description":"116 images found, automatically creating validation set","severity":"good"},{"description":"Smallest class is \"Dog\" with 51 images","severity":"debug"},{"description":"Largest class is \"Ong\" with 65 images","severity":"debug"}],"classifierAnalysis":{"columns":[],"vizualizerSpec":"","labelStats":{"Dog":51,"Ong":65}}}},"dataURL":"file:\/\/\/Users\/beomsookim\/Desktop\/IOS_FastCampus\/CoreML\/Ongs-100\/","featureExtractionCheckpointMayBeAvailable":false,"recipeValidationResults":{"imageClassifier":{"confusionMatrix":[{"expected":"Dog","actual":"Dog","count":8},{"expected":"Ong","actual":"Dog","count":1},{"expected":"Ong","actual":"Ong","count":5}],"statsByLabel":{"Dog":{"count":9,"precisionRecall":{"success":{"recall":0.88888888888888884,"precision":1}}},"Ong":{"count":5,"precisionRecall":{"success":{"recall":1,"precision":0.83333333333333337}}}},"accuracy":0.9285714285714286}},"progress":[{"currentRowIndex":0,"tableIndex":0,"count":0,"isLast":false,"percentComplete":0,"tableDone":false},{"icTrainingColumnHeader":{"hasValidation":true,"elapsedTime":0.027400999999999998,"trainingAccuracy":0.58823499999999995,"iterationCount":1,"validationAccuracy":0.35714299999999999},"isLast":false,"currentRowIndex":0,"count":1,"tableDone":false,"tableIndex":24,"percentComplete":0},{"icTrainingColumnHeader":{"hasValidation":true,"elapsedTime":0.069287999999999988,"trainingAccuracy":0.95098000000000005,"iterationCount":2,"validationAccuracy":0.85714299999999999},"isLast":false,"currentRowIndex":0,"count":2,"tableDone":false,"tableIndex":24,"percentComplete":0},{"icTrainingColumnHeader":{"hasValidation":true,"elapsedTime":0.091197,"trainingAccuracy":1,"iterationCount":3,"validationAccuracy":0.92857100000000004},"isLast":false,"currentRowIndex":0,"count":3,"tableDone":false,"tableIndex":24,"percentComplete":0},{"icTrainingColumnHeader":{"hasValidation":true,"elapsedTime":0.106768,"trainingAccuracy":1,"iterationCount":4,"validationAccuracy":0.92857100000000004},"isLast":false,"currentRowIndex":0,"count":4,"tableDone":false,"tableIndex":24,"percentComplete":0},{"icTrainingColumnHeader":{"hasValidation":true,"elapsedTime":0.12027,"trainingAccuracy":1,"iterationCount":5,"validationAccuracy":0.92857100000000004},"isLast":false,"currentRowIndex":0,"count":5,"tableDone":false,"tableIndex":24,"percentComplete":0},{"icTrainingColumnHeader":{"hasValidation":true,"elapsedTime":0.22634599999999999,"trainingAccuracy":1,"iterationCount":10,"validationAccuracy":0.92857100000000004},"isLast":false,"currentRowIndex":0,"count":10,"tableDone":true,"tableIndex":24,"percentComplete":0},{"currentRowIndex":0,"tableIndex":0,"count":15,"isLast":false,"percentComplete":0,"tableDone":false},{"currentRowIndex":0,"tableIndex":0,"count":20,"isLast":false,"percentComplete":0,"tableDone":false},{"currentRowIndex":0,"tableIndex":0,"count":25,"isLast":false,"percentComplete":0,"tableDone":false},{"currentRowIndex":0,"tableIndex":0,"count":30,"isLast":false,"percentComplete":0,"tableDone":false},{"currentRowIndex":0,"tableIndex":0,"count":35,"isLast":false,"percentComplete":0,"tableDone":false},{"currentRowIndex":0,"tableIndex":0,"count":40,"isLast":false,"percentComplete":0,"tableDone":false},{"currentRowIndex":0,"tableIndex":0,"count":45,"isLast":false,"percentComplete":0,"tableDone":false},{"currentRowIndex":0,"tableIndex":0,"count":50,"isLast":false,"percentComplete":0,"tableDone":false},{"currentRowIndex":0,"tableIndex":0,"count":55,"isLast":false,"percentComplete":0,"tableDone":false},{"currentRowIndex":0,"tableIndex":0,"count":60,"isLast":false,"percentComplete":0,"tableDone":false},{"currentRowIndex":0,"tableIndex":0,"count":65,"isLast":false,"percentComplete":0,"tableDone":false},{"currentRowIndex":0,"tableIndex":0,"count":70,"isLast":false,"percentComplete":0,"tableDone":false},{"currentRowIndex":0,"tableIndex":0,"count":75,"isLast":false,"percentComplete":0,"tableDone":false},{"currentRowIndex":0,"tableIndex":0,"count":80,"isLast":false,"percentComplete":0,"tableDone":false},{"currentRowIndex":0,"tableIndex":0,"count":85,"isLast":false,"percentComplete":0,"tableDone":false},{"currentRowIndex":0,"tableIndex":0,"count":90,"isLast":false,"percentComplete":0,"tableDone":false},{"currentRowIndex":0,"tableIndex":0,"count":95,"isLast":false,"percentComplete":0,"tableDone":false},{"currentRowIndex":0,"tableIndex":0,"count":100,"isLast":false,"percentComplete":0,"tableDone":false},{"currentRowIndex":0,"tableIndex":0,"count":105,"isLast":false,"percentComplete":0,"tableDone":false},{"currentRowIndex":0,"tableIndex":0,"count":110,"isLast":false,"percentComplete":0,"tableDone":false},{"currentRowIndex":0,"tableIndex":0,"count":115,"isLast":false,"percentComplete":0,"tableDone":false},{"currentRowIndex":0,"tableIndex":0,"count":116,"isLast":false,"percentComplete":0,"tableDone":true}],"trainingAccuracy":1,"checkpointMetrics":{},"analysedDataType":"none","dataSourceID":"180EE8B1-3F39-48A8-A1CC-1F05EEA48E37","snapshottableCheckpoints":{},"validationAccuracy":0.9285714285714286,"startTime":"2021-07-29T07:29:41Z"},"createdDate":"2021-07-29T07:29:16Z","snapshotRole":{"withoutSnapshots":0},"evaluationEntities":[{"result":{"imageClassifier":{"statsByLabel":{"Dog":{"count":100,"precisionRecall":{"success":{"recall":0.97999999999999998,"precision":1}}},"Ong":{"count":112,"precisionRecall":{"success":{"recall":1,"precision":0.98245614035087714}}}},"accuracy":0.99056603773584906}},"dataURL":"file:\/\/\/Users\/beomsookim\/Desktop\/IOS_FastCampus\/CoreML\/Ongs-Testing\/","id":"53df5323-d135-424c-9a17-dbdde3e3d6d4","dataResult":{"itemsCount":212,"dataURL":"file:\/\/\/Users\/beomsookim\/Desktop\/IOS_FastCampus\/CoreML\/Ongs-Testing\/","classesCount":2,"dataSourceID":"302A6CEF-3065-4A63-93C3-AF1343ABED40","analysis":{"summary":{"sampleCount":212,"classCount":2,"canUseValidation":1},"issues":[{"description":"2 classes found, including Ong, Dog","severity":"debug"},{"description":"212 images found, automatically creating validation set","severity":"good"},{"description":"Smallest class is \"Dog\" with 100 images","severity":"debug"},{"description":"Largest class is \"Ong\" with 112 images","severity":"debug"}],"classifierAnalysis":{"columns":[],"vizualizerSpec":"","labelStats":{"Dog":100,"Ong":112}}}},"dataSourceID":"302A6CEF-3065-4A63-93C3-AF1343ABED40","analysedDataType":"none","accuracy":0.99056603773584906,"startTime":"2021-07-29T07:29:44Z","finishTime":"2021-07-29T07:29:45Z"},{"id":"ca03c1f7-e609-4932-b8b0-e1afe836dedf","dataResult":{"itemsCount":212,"dataURL":"file:\/\/\/Users\/beomsookim\/Desktop\/IOS_FastCampus\/CoreML\/Ongs-Testing\/","classesCount":2,"dataSourceID":"302A6CEF-3065-4A63-93C3-AF1343ABED40","analysis":{"summary":{"sampleCount":212,"classCount":2,"canUseValidation":1},"issues":[{"description":"2 classes found, including Ong, Dog","severity":"debug"},{"description":"212 images found, automatically creating validation set","severity":"good"},{"description":"Smallest class is \"Dog\" with 100 images","severity":"debug"},{"description":"Largest class is \"Ong\" with 112 images","severity":"debug"}],"classifierAnalysis":{"columns":[],"vizualizerSpec":"","labelStats":{"Dog":100,"Ong":112}}}},"dataURL":"file:\/\/\/Users\/beomsookim\/Desktop\/IOS_FastCampus\/CoreML\/Ongs-Testing\/","dataSourceID":"302A6CEF-3065-4A63-93C3-AF1343ABED40","analysedDataType":"none"}],"activityEntities":["evaluationStarted",[{"id":"59F6C877-8912-4AB3-8550-E0868617016B","title":"Testing Started","createdDate":"2021-07-29T07:29:44Z","event":"evaluationStarted","subtitle":"MyOngDogClassifier 1"}],"trainingStarted",[{"id":"F1A47B61-7A69-4FE3-8705-3D709158280A","title":"Training Started","createdDate":"2021-07-29T07:29:41Z","event":"trainingStarted","subtitle":"25 iterations"}],"experimentCreated",[{"id":"30CB20A0-B471-4E90-AFFE-853EB3B17424","title":"Model Source Created","createdDate":"2021-07-29T07:29:16Z","event":"experimentCreated","subtitle":"MyOngDogClassifier 1"}],"trainingFinished",[{"id":"1A5120EA-8FC9-4978-A2EA-CB8BA33F120C","title":"Training Completed","createdDate":"2021-07-29T07:29:42Z","event":"trainingFinished","subtitle":"Model converged at 10 iterations"}],"trainingDataAdded",[{"id":"4C522522-C304-46FE-B368-DFEE3AEBABAE","title":"Training Data Added","createdDate":"2021-07-29T07:29:21Z","event":"trainingDataAdded","subtitle":"Ongs-100"}],"evaluationFinished",[{"id":"DEAB189E-991E-4D0A-9ADB-B6A726A3DF65","title":"Testing Completed","createdDate":"2021-07-29T07:29:45Z","event":"evaluationFinished","subtitle":"MyOngDogClassifier 1"}],"evaluationDataAdded",[{"id":"F6ED78F0-F83F-40A0-8072-0B39EF0E723B","title":"Testing Data Added","createdDate":"2021-07-29T07:29:29Z","event":"evaluationDataAdded","subtitle":"Ongs-Testing"}]],"title":"MyOngDogClassifier 1","evaluationEntity":{"result":{"imageClassifier":{"statsByLabel":{"Dog":{"count":100,"precisionRecall":{"success":{"recall":0.97999999999999998,"precision":1}}},"Ong":{"count":112,"precisionRecall":{"success":{"recall":1,"precision":0.98245614035087714}}}},"accuracy":0.99056603773584906}},"dataURL":"file:\/\/\/Users\/beomsookim\/Desktop\/IOS_FastCampus\/CoreML\/Ongs-Testing\/","id":"f3cd3b7f-9d56-4259-b763-0ab4821bfcae","dataResult":{"itemsCount":212,"dataURL":"file:\/\/\/Users\/beomsookim\/Desktop\/IOS_FastCampus\/CoreML\/Ongs-Testing\/","classesCount":2,"dataSourceID":"302A6CEF-3065-4A63-93C3-AF1343ABED40","analysis":{"summary":{"canUseValidation":1,"classCount":2,"sampleCount":212},"issues":[{"description":"2 classes found, including Ong, Dog","severity":"debug"},{"description":"212 images found, automatically creating validation set","severity":"good"},{"description":"Smallest class is \"Dog\" with 100 images","severity":"debug"},{"description":"Largest class is \"Ong\" with 112 images","severity":"debug"}],"classifierAnalysis":{"columns":[],"vizualizerSpec":"","labelStats":{"Dog":100,"Ong":112}}}},"dataSourceID":"302A6CEF-3065-4A63-93C3-AF1343ABED40","analysedDataType":"none","accuracy":0.99056603773584906,"startTime":"2021-07-29T07:29:44Z","finishTime":"2021-07-29T07:29:45Z"},"evaluationState":"evaluated","contentDataResult":{},"modifiedDate":"2021-07-29T07:29:45Z","preferredFilename":"MyOngDogClassifier 1"}